glaciotrack/__init__.py
glaciotrack/offsettracking.py
glaciotrack-0.1.1.dist-info/LICENSE.txt
glaciotrack-0.1.1.dist-info/METADATA
glaciotrack-0.1.1.dist-info/WHEEL
glaciotrack-0.1.1.dist-info/top_level.txt
glaciotrack-0.1.1.dist-info/RECORD
