Metadata-Version: 2.2
Name: glaciotrack
Version: 0.1.1
Summary: A Python package to process Sentinel-1 data for glacier velocity estimation.
Home-page: https://github.com/Virginia555
Author: Virginia Valeri
Author-email: virginiavaleri555@gmail.com
License: MIT
Keywords: sentinel-1 glacier velocity offset tracking remote sensing
Classifier: Development Status :: 5 - Production/Stable
Classifier: Intended Audience :: Science/Research
Classifier: Operating System :: OS Independent
Classifier: License :: OSI Approved :: MIT License
Classifier: Programming Language :: Python :: 3
Classifier: Programming Language :: Python :: 3.8
Classifier: Programming Language :: Python :: 3.9
Classifier: Programming Language :: Python :: 3.10
License-File: LICENSE.txt
Requires-Dist: geopandas<1.0.0,>=0.10.0
Requires-Dist: snappy<4.0.0,>=2.0.0
Requires-Dist: numpy<2.0.0,>=1.21.0
Requires-Dist: matplotlib<4.0.0,>=3.4.0
Requires-Dist: scipy<2.0.0,>=1.6.0
Dynamic: author
Dynamic: author-email
Dynamic: classifier
Dynamic: description
Dynamic: description-content-type
Dynamic: home-page
Dynamic: keywords
Dynamic: license
Dynamic: requires-dist
Dynamic: summary
